{"Exif":{"Lat":0,"Long":0,"Date":"2018-08-09T08:36:07-04:00","Tags":{"ApertureValue":5,"ComponentsConfiguration":"","CustomRendered|int":"0","DateTimeDigitized|time.Time":"2018-08-09T08:36:07-04:00","DateTimeOriginal|time.Time":"2018-08-09T08:36:07-04:00","DateTime|time.Time":"2018-08-09T08:36:07-04:00","ExposureTime|*big.Rat":"1/125","FNumber":5.6,"FocalLength":135,"ISOSpeedRatings|int":"800","ImageUniqueID":"6cca6aa9423027eb0000000000000000","Make":"Canon","MaxApertureValue":5.187358218189317,"Model":"Canon EOS 40D","PixelXDimension|int":"3888","PixelYDimension|int":"2592","SceneCaptureType|int":"0","ShutterSpeedValue":7,"Software":"Picasa","SubSecTime":"90","SubSecTimeDigitized":"90","SubSecTimeOriginal":"90"}}}
