{"Exif":{"Lat":0,"Long":0,"Date":"2022-08-09T07:11:28-04:00","Tags":{"ApertureValue":6,"Artist":"","ComponentsConfiguration":"","Copyright":"","DateTimeOriginal|time.Time":"2022-08-09T07:11:28-04:00","DateTime|time.Time":"2022-10-19T22:29:24-04:00","ExposureTime|*big.Rat":"1/400","FNumber":8,"FocalLength":18,"ISOSpeedRatings|int":"500","ImageUniqueID":"524cca7cb4f44cc88ac7595547731554","LensModel":"18-35mm F1.8 DC HSM | Art 013","Make":"Canon","Model":"Canon EOS 90D","Orientation|int":"1","PixelXDimension|int":"6960","PixelYDimension|int":"4640","SceneCaptureType|int":"0","ShutterSpeedValue":8.625708884688091,"SubSecTimeOriginal":"81","UserComment":"ASCII"}}}
